providers/.gitignore
providers/.native
providers/README.md
providers/__init__.py
providers/arithmatic/.tackle.meta.yaml
providers/arithmatic/hooks/arithmatic.py
providers/arithmatic/tests/test_average.py
providers/arithmatic/tests/test_modulo.py
providers/arithmatic/tests/test_sum.py
providers/collections/.tackle.meta.yaml
providers/collections/notes.md
providers/collections/hooks/concatenate.py
providers/collections/hooks/distinct.py
providers/collections/hooks/list_key.py
providers/collections/hooks/map_to_list_key_values.py
providers/collections/hooks/range.py
providers/collections/hooks/sort.py
providers/collections/tests/concatenate.yaml
providers/collections/tests/distinct.yaml
providers/collections/tests/list-keys.yaml
providers/collections/tests/range.yaml
providers/collections/tests/sort-in-place.yaml
providers/collections/tests/sort-map-func.yaml
providers/collections/tests/sort-map-keys.yaml
providers/collections/tests/sort-map.yaml
providers/collections/tests/test_provider_collections.py
providers/command/.tackle.meta.yaml
providers/command/hooks/command.py
providers/command/hooks/system.py
providers/command/tests/exit-ignore.yaml
providers/command/tests/exit-long.yaml
providers/command/tests/exit.yaml
providers/command/tests/interactive.yaml
providers/command/tests/list-dir.yaml
providers/command/tests/multi-line-cmd.yaml
providers/command/tests/test_provider_command.py
providers/console/.tackle.meta.yaml
providers/console/requirements.txt
providers/console/hooks/markdown.py
providers/console/hooks/prints.py
providers/console/hooks/table.py
providers/console/tests/frontmatter-none.md
providers/console/tests/frontmatter.md
providers/console/tests/markdown.yaml
providers/console/tests/pprint.yaml
providers/console/tests/print.yaml
providers/console/tests/table.yaml
providers/console/tests/table_split.yaml
providers/console/tests/test_provider_console_print.py
providers/console/tests/test_provider_console_rich.py
providers/context/.tackle.meta.yaml
tackle-0.7.6.dist-info/licenses/LICENSE
tackle-0.7.6.dist-info/METADATA
tackle-0.7.6.dist-info/WHEEL
tackle-0.7.6.dist-info/entry_points.txt
tackle-0.7.6.dist-info/top_level.txt
tackle-0.7.6.dist-info/RECORD
