Metadata-Version: 2.4
Name: tackle
Version: 0.7.6
Summary: Tackle is a declarative DSL for building modular workflows and code generators. Tool is plugins based and can easily be extended by writing additional hooks or importing external providers that can be turned into a self documenting CLI, all out of yaml, json, toml.
Home-page: https://github.com/sudoblockio/tackle
Author: Rob Cannon
Author-email: robc.io.opensource@gmail.com
License: BSD
Keywords: tackle,tackle-box,tacklebox,tackle box,Python,projects,Jinja2,project templates,cookiecutter,skeleton,scaffolding,project directory,package,packaging,kubernetes,config file management,configuration language,declarative cli
Classifier: Development Status :: 5 - Production/Stable
Classifier: Environment :: Console
Classifier: Intended Audience :: Developers
Classifier: Natural Language :: English
Classifier: License :: OSI Approved :: BSD License
Classifier: Programming Language :: Python :: 3 :: Only
Classifier: Programming Language :: Python :: 3
Classifier: Programming Language :: Python :: 3.10
Classifier: Programming Language :: Python :: 3.11
Classifier: Programming Language :: Python :: 3.12
Classifier: Programming Language :: Python :: Implementation :: CPython
Classifier: Programming Language :: Python :: Implementation :: PyPy
Classifier: Programming Language :: Python
Classifier: Topic :: Software Development
Requires-Python: >=3.10
License-File: LICENSE
Requires-Dist: Jinja2>3.0.0
Requires-Dist: requests>=2.23.0
Requires-Dist: pydantic>=2.4.2
Requires-Dist: pydantic-settings>2.0.0
Requires-Dist: InquirerPy>=0.3.3
Requires-Dist: ruyaml==0.91.0
Requires-Dist: rich>=12.6.0
Requires-Dist: xdg==5.1.1
Requires-Dist: tomli>=1.0.0; python_version == "3.10"
Dynamic: author
Dynamic: author-email
Dynamic: classifier
Dynamic: description
Dynamic: description-content-type
Dynamic: home-page
Dynamic: keywords
Dynamic: license
Dynamic: license-file
Dynamic: provides-extra
Dynamic: requires-dist
Dynamic: requires-python
Dynamic: summary
